partcad_skyline/__init__.py
partcad_skyline/skyline.py
partcad_skyline-0.1.1a2.dist-info/LICENSE
partcad_skyline-0.1.1a2.dist-info/METADATA
partcad_skyline-0.1.1a2.dist-info/WHEEL
partcad_skyline-0.1.1a2.dist-info/entry_points.txt
partcad_skyline-0.1.1a2.dist-info/RECORD
